local_weather_mcp/__init__.py
local_weather_mcp/server.py
local_weather_mcp-0.1.8.dist-info/METADATA
local_weather_mcp-0.1.8.dist-info/WHEEL
local_weather_mcp-0.1.8.dist-info/entry_points.txt
local_weather_mcp-0.1.8.dist-info/top_level.txt
local_weather_mcp-0.1.8.dist-info/RECORD
