Metadata-Version: 2.4
Name: local-weather-mcp
Version: 0.1.8
Requires-Dist: mcp[cli]
Requires-Dist: httpx
